setup.py
client/__init__.py
client/add_contact.py
client/cl_main_window.py
client/cl_main_window_gui.py
client/client_database.py
client/del_contact.py
client/start_dialog.py
client/transport.py
client_mess_app.egg-info/PKG-INFO
client_mess_app.egg-info/SOURCES.txt
client_mess_app.egg-info/dependency_links.txt
client_mess_app.egg-info/requires.txt
client_mess_app.egg-info/top_level.txt
common/__init__.py
common/decorators.py
common/descriptors.py
common/errors.py
common/metaclasses.py
common/utilities.py
common/vars.py
docs/__init__.py
docs/source/__init__.py
docs/source/conf.py
logs/__init__.py
logs/configs_logs/__init__.py
logs/configs_logs/config_client_log.py
logs/configs_logs/config_server_log.py
project_unittests/__init__.py
project_unittests/test_client.py
project_unittests/test_server.py
project_unittests/test_utils.py