Metadata-Version: 1.0
Name: client-mess-app
Version: 0.0.1
Summary: client_messenger_app
Home-page: UNKNOWN
Author: Aleksandr Kositsyn
Author-email: kos_off@mail.ru
License: UNKNOWN
Platform: UNKNOWN
